CHANGES.rst
CONTRIBUTORS.rst
DEVELOP.rst
LICENSE.rst
MANIFEST.in
README.rst
setup.cfg
setup.py
docs/Configuring_Your_IFTTT_Secret_Key.rst
docs/Enable_RSS_feed_on_Plone.rst
docs/IFTTT_Easyform_Action.rst
docs/IFTTT_Trigger_and_Applet.rst
docs/Introduction_to_IFTTT_Applets.rst
docs/Makefile
docs/Trigger_IFTTT_Action.rst
docs/Using_Plone_RSS_Feeds_in_IFTTT_Applets.rst
docs/What_is_IFTTT.rst
docs/conf.py
docs/content_trigger.rst
docs/event_trigger.rst
docs/index.rst
docs/make.bat
docs/manage_trigger.rst
docs/user_trigger.rst
docs/_screenshots/__init__.robot
docs/_screenshots/keywords.robot
docs/_screenshots/test_controlpanel.robot
docs/_screenshots/test_example.robot
docs/_static/images/Enable_Rss_Feed/Enable_RSS/Step1.png
docs/_static/images/Enable_Rss_Feed/Enable_RSS/Step2.png
docs/_static/images/Enable_Rss_Feed/Enable_RSS/Step3.png
docs/_static/images/Enable_Rss_Feed/creating_collection/Enable_feed_icon.png
docs/_static/images/Enable_Rss_Feed/creating_collection/Step1.png
docs/_static/images/Enable_Rss_Feed/creating_collection/Step2.png
docs/_static/images/Enable_Rss_Feed/creating_collection/Step3.png
docs/_static/images/Enable_Rss_Feed/creating_collection/Step4.png
docs/_static/images/Enable_Rss_Feed/creating_collection/Step7.png
docs/_static/images/Enable_Rss_Feed/creating_collection/Step8.png
docs/_static/images/Enable_Rss_Feed/creating_collection/feed_icon_on_folder.png
docs/_static/images/Enable_Rss_Feed/creating_collection/publish_collection.png
docs/_static/images/Enable_Rss_Feed/creating_collection/settings_tab.png
docs/_static/images/Enable_Rss_Feed/creating_collection/syndication_tab.png
docs/_static/images/Trigger_IFTTT_Action/Content_Rules_on_site_setup.png
docs/_static/images/Trigger_IFTTT_Action/IFTTT_trigger.png
docs/_static/images/Trigger_IFTTT_Action/add_content_rule.png
docs/_static/images/Trigger_IFTTT_Action/configure_action.png
docs/_static/images/Trigger_IFTTT_Action/configure_content_rule.png
src/collective.ifttt.egg-info/PKG-INFO
src/collective.ifttt.egg-info/SOURCES.txt
src/collective.ifttt.egg-info/dependency_links.txt
src/collective.ifttt.egg-info/entry_points.txt
src/collective.ifttt.egg-info/namespace_packages.txt
src/collective.ifttt.egg-info/not-zip-safe
src/collective.ifttt.egg-info/requires.txt
src/collective.ifttt.egg-info/top_level.txt
